[
  {
    "title": "How to Customize Your Etsy Purchases Using Adobe Express",
    "slug": "adobe-express-etsy",
    "excerpt": "Learn to customize your Etsy digital downloads with Adobe Express for free. Step-by-step guide to editing receipts, invoices, and planners.",
    "content": {
      "type": "doc",
      "content": [
        {
          "type": "paragraph",
          "content": [
            {
              "type": "text",
              "text": "So you've just purchased a beautiful digital template from Etsy—a receipt book, planner, or invoice template—but now you need to customize it with your business name, logo, and details. The great news? You don't need expensive software to do it."
            }
          ]
        },
        {
          "type": "paragraph",
          "content": [
            {
              "type": "text",
              "text": "Adobe Express (formerly Adobe Spark) offers a free, browser-based design tool that makes customizing PDFs and templates surprisingly simple. This guide walks you through the entire process."
            }
          ]
        },
        {
          "type": "heading",
          "attrs": {
            "level": 2
          },
          "content": [
            {
              "type": "text",
              "text": "What You'll Need"
            }
          ]
        },
        {
          "type": "bulletList",
          "content": [
            {
              "type": "listItem",
              "content": [
                {
                  "type": "paragraph",
                  "content": [
                    {
                      "type": "text",
                      "text": "Your purchased Etsy digital download (usually a PDF or image file)"
                    }
                  ]
                }
              ]
            },
            {
              "type": "listItem",
              "content": [
                {
                  "type": "paragraph",
                  "content": [
                    {
                      "type": "text",
                      "text": "A free Adobe Express account"
                    }
                  ]
                }
              ]
            },
            {
              "type": "listItem",
              "content": [
                {
                  "type": "paragraph",
                  "content": [
                    {
                      "type": "text",
                      "text": "Your business logo and details (optional but recommended)"
                    }
                  ]
                }
              ]
            },
            {
              "type": "listItem",
              "content": [
                {
                  "type": "paragraph",
                  "content": [
                    {
                      "type": "text",
                      "text": "About 15-20 minutes"
                    }
                  ]
                }
              ]
            }
          ]
        },
        {
          "type": "heading",
          "attrs": {
            "level": 2
          },
          "content": [
            {
              "type": "text",
              "text": "Step 1: Download Your Etsy Purchase"
            }
          ]
        },
        {
          "type": "paragraph",
          "content": [
            {
              "type": "text",
              "text": "After completing your Etsy purchase, navigate to your Purchases and Reviews section. Download all the files—many sellers include multiple file formats (PDF, PNG, JPEG) to give you flexibility."
            }
          ]
        },
        {
          "type": "callout",
          "attrs": {
            "variant": "info"
          },
          "content": [
            {
              "type": "paragraph",
              "content": [
                {
                  "type": "text",
                  "text": "Pro tip: Save your files in a dedicated folder on your computer so you can easily find them later."
                }
              ]
            }
          ]
        },
        {
          "type": "heading",
          "attrs": {
            "level": 2
          },
          "content": [
            {
              "type": "text",
              "text": "Step 2: Create Your Free Adobe Express Account"
            }
          ]
        },
        {
          "type": "paragraph",
          "content": [
            {
              "type": "text",
              "text": "Visit "
            },
            {
              "type": "text",
              "text": "Adobe Express",
              "marks": [
                {
                  "type": "link",
                  "attrs": {
                    "href": "https://express.adobe.com"
                  }
                }
              ]
            },
            {
              "type": "text",
              "text": " and sign up for a free account. You can use your Google, Facebook, or email to register. The free tier includes everything you need for basic customization."
            }
          ]
        },
        {
          "type": "heading",
          "attrs": {
            "level": 2
          },
          "content": [
            {
              "type": "text",
              "text": "Step 3: Import Your Template"
            }
          ]
        },
        {
          "type": "paragraph",
          "content": [
            {
              "type": "text",
              "text": "Once logged in, click \"Create new\" and select the appropriate size for your document. For letter-size templates (most common for receipts and invoices), choose 8.5 x 11 inches."
            }
          ]
        },
        {
          "type": "paragraph",
          "content": [
            {
              "type": "text",
              "text": "Upload your Etsy template by clicking \"Upload\" and selecting your file. If it's a PDF, Adobe Express will convert it to an editable format."
            }
          ]
        },
        {
          "type": "heading",
          "attrs": {
            "level": 2
          },
          "content": [
            {
              "type": "text",
              "text": "Step 4: Customize Your Template"
            }
          ]
        },
        {
          "type": "paragraph",
          "content": [
            {
              "type": "text",
              "text": "Now comes the fun part! Here's what you can typically customize:"
            }
          ]
        },
        {
          "type": "bulletList",
          "content": [
            {
              "type": "listItem",
              "content": [
                {
                  "type": "paragraph",
                  "content": [
                    {
                      "type": "text",
                      "text": "Business name and contact information"
                    }
                  ]
                }
              ]
            },
            {
              "type": "listItem",
              "content": [
                {
                  "type": "paragraph",
                  "content": [
                    {
                      "type": "text",
                      "text": "Logo placement and sizing"
                    }
                  ]
                }
              ]
            },
            {
              "type": "listItem",
              "content": [
                {
                  "type": "paragraph",
                  "content": [
                    {
                      "type": "text",
                      "text": "Colors to match your brand"
                    }
                  ]
                }
              ]
            },
            {
              "type": "listItem",
              "content": [
                {
                  "type": "paragraph",
                  "content": [
                    {
                      "type": "text",
                      "text": "Fonts (if the template allows)"
                    }
                  ]
                }
              ]
            },
            {
              "type": "listItem",
              "content": [
                {
                  "type": "paragraph",
                  "content": [
                    {
                      "type": "text",
                      "text": "Pre-filled information like your address or tax ID"
                    }
                  ]
                }
              ]
            }
          ]
        },
        {
          "type": "heading",
          "attrs": {
            "level": 2
          },
          "content": [
            {
              "type": "text",
              "text": "Step 5: Export and Use"
            }
          ]
        },
        {
          "type": "paragraph",
          "content": [
            {
              "type": "text",
              "text": "When you're satisfied with your customizations, click \"Download\" and choose your preferred format:"
            }
          ]
        },
        {
          "type": "bulletList",
          "content": [
            {
              "type": "listItem",
              "content": [
                {
                  "type": "paragraph",
                  "content": [
                    {
                      "type": "text",
                      "text": "PDF: Best for printing or emailing to customers"
                    }
                  ]
                }
              ]
            },
            {
              "type": "listItem",
              "content": [
                {
                  "type": "paragraph",
                  "content": [
                    {
                      "type": "text",
                      "text": "PNG: Good for digital use with transparent backgrounds"
                    }
                  ]
                }
              ]
            },
            {
              "type": "listItem",
              "content": [
                {
                  "type": "paragraph",
                  "content": [
                    {
                      "type": "text",
                      "text": "JPEG: Smaller file size, good for web use"
                    }
                  ]
                }
              ]
            }
          ]
        },
        {
          "type": "heading",
          "attrs": {
            "level": 2
          },
          "content": [
            {
              "type": "text",
              "text": "Tips for Best Results"
            }
          ]
        },
        {
          "type": "bulletList",
          "content": [
            {
              "type": "listItem",
              "content": [
                {
                  "type": "paragraph",
                  "content": [
                    {
                      "type": "text",
                      "text": "Keep your original downloaded file as a backup"
                    }
                  ]
                }
              ]
            },
            {
              "type": "listItem",
              "content": [
                {
                  "type": "paragraph",
                  "content": [
                    {
                      "type": "text",
                      "text": "Create multiple versions if you need different layouts"
                    }
                  ]
                }
              ]
            },
            {
              "type": "listItem",
              "content": [
                {
                  "type": "paragraph",
                  "content": [
                    {
                      "type": "text",
                      "text": "Test print one copy before printing in bulk"
                    }
                  ]
                }
              ]
            },
            {
              "type": "listItem",
              "content": [
                {
                  "type": "paragraph",
                  "content": [
                    {
                      "type": "text",
                      "text": "Save your Adobe Express project so you can make future edits"
                    }
                  ]
                }
              ]
            }
          ]
        },
        {
          "type": "callout",
          "attrs": {
            "variant": "success"
          },
          "content": [
            {
              "type": "paragraph",
              "content": [
                {
                  "type": "text",
                  "text": "That's it! You've successfully customized your Etsy purchase using a free tool. No expensive software required."
                }
              ]
            }
          ]
        },
        {
          "type": "heading",
          "attrs": {
            "level": 2
          },
          "content": [
            {
              "type": "text",
              "text": "Need Templates to Customize?"
            }
          ]
        },
        {
          "type": "paragraph",
          "content": [
            {
              "type": "text",
              "text": "Check out our collection of "
            },
            {
              "type": "text",
              "text": "business templates on Etsy",
              "marks": [
                {
                  "type": "link",
                  "attrs": {
                    "href": "https://www.etsy.com/shop/simplebiztoolkit"
                  }
                }
              ]
            },
            {
              "type": "text",
              "text": "—all designed to be easily customizable with tools like Adobe Express."
            }
          ]
        }
      ]
    },
    "coverImageUrl": "/images/articles/adobe-express-etsy.jpg",
    "status": "published",
    "publishedAt": "2024-12-15T00:00:00.000Z",
    "seoTitle": "How to Customize Your Etsy Purchases Using Adobe Express",
    "seoDescription": "Learn to customize your Etsy digital downloads with Adobe Express for free. Step-by-step guide to editing receipts, invoices, and planners.",
    "tagIds": [],
    "legacySlug": "adobe-express-etsy"
  },
  {
    "title": "Bookkeeping Basics Without an Accountant",
    "slug": "bookkeeping-basics-without-an-accountant",
    "excerpt": "No accountant? No problem. Learn simple bookkeeping practices that keep your finances organized without professional help.",
    "content": {
      "type": "doc",
      "content": [
        {
          "type": "paragraph",
          "content": [
            {
              "type": "text",
              "text": "Running a small business doesn't mean you need to hire an accountant right away. With some basic knowledge and the right tools, you can handle your own bookkeeping effectively."
            }
          ]
        },
        {
          "type": "heading",
          "attrs": {
            "level": 2
          },
          "content": [
            {
              "type": "text",
              "text": "Why DIY Bookkeeping Makes Sense"
            }
          ]
        },
        {
          "type": "paragraph",
          "content": [
            {
              "type": "text",
              "text": "For many small businesses—especially side hustles and early-stage ventures—hiring an accountant isn't financially practical. The good news is that basic bookkeeping is learnable, and staying organized yourself has benefits:"
            }
          ]
        },
        {
          "type": "bulletList",
          "content": [
            {
              "type": "listItem",
              "content": [
                {
                  "type": "paragraph",
                  "content": [
                    {
                      "type": "text",
                      "text": "You understand your finances better"
                    }
                  ]
                }
              ]
            },
            {
              "type": "listItem",
              "content": [
                {
                  "type": "paragraph",
                  "content": [
                    {
                      "type": "text",
                      "text": "You catch issues early"
                    }
                  ]
                }
              ]
            },
            {
              "type": "listItem",
              "content": [
                {
                  "type": "paragraph",
                  "content": [
                    {
                      "type": "text",
                      "text": "You're prepared when you do hire help"
                    }
                  ]
                }
              ]
            },
            {
              "type": "listItem",
              "content": [
                {
                  "type": "paragraph",
                  "content": [
                    {
                      "type": "text",
                      "text": "You save money in the early stages"
                    }
                  ]
                }
              ]
            }
          ]
        },
        {
          "type": "heading",
          "attrs": {
            "level": 2
          },
          "content": [
            {
              "type": "text",
              "text": "The Core Bookkeeping Tasks"
            }
          ]
        },
        {
          "type": "heading",
          "attrs": {
            "level": 3
          },
          "content": [
            {
              "type": "text",
              "text": "1. Track Every Transaction"
            }
          ]
        },
        {
          "type": "paragraph",
          "content": [
            {
              "type": "text",
              "text": "Record every dollar that comes in and goes out. This includes:"
            }
          ]
        },
        {
          "type": "bulletList",
          "content": [
            {
              "type": "listItem",
              "content": [
                {
                  "type": "paragraph",
                  "content": [
                    {
                      "type": "text",
                      "text": "Sales and income"
                    }
                  ]
                }
              ]
            },
            {
              "type": "listItem",
              "content": [
                {
                  "type": "paragraph",
                  "content": [
                    {
                      "type": "text",
                      "text": "Business expenses"
                    }
                  ]
                }
              ]
            },
            {
              "type": "listItem",
              "content": [
                {
                  "type": "paragraph",
                  "content": [
                    {
                      "type": "text",
                      "text": "Transfers between accounts"
                    }
                  ]
                }
              ]
            },
            {
              "type": "listItem",
              "content": [
                {
                  "type": "paragraph",
                  "content": [
                    {
                      "type": "text",
                      "text": "Payments to yourself"
                    }
                  ]
                }
              ]
            }
          ]
        },
        {
          "type": "heading",
          "attrs": {
            "level": 3
          },
          "content": [
            {
              "type": "text",
              "text": "2. Keep Receipts Organized"
            }
          ]
        },
        {
          "type": "paragraph",
          "content": [
            {
              "type": "text",
              "text": "The IRS requires documentation for business expenses. Create a simple system:"
            }
          ]
        },
        {
          "type": "bulletList",
          "content": [
            {
              "type": "listItem",
              "content": [
                {
                  "type": "paragraph",
                  "content": [
                    {
                      "type": "text",
                      "text": "Take photos of physical receipts immediately"
                    }
                  ]
                }
              ]
            },
            {
              "type": "listItem",
              "content": [
                {
                  "type": "paragraph",
                  "content": [
                    {
                      "type": "text",
                      "text": "Create folders by month or category"
                    }
                  ]
                }
              ]
            },
            {
              "type": "listItem",
              "content": [
                {
                  "type": "paragraph",
                  "content": [
                    {
                      "type": "text",
                      "text": "Use apps like Expensify or simply a dedicated email folder"
                    }
                  ]
                }
              ]
            },
            {
              "type": "listItem",
              "content": [
                {
                  "type": "paragraph",
                  "content": [
                    {
                      "type": "text",
                      "text": "Match receipts to transactions weekly"
                    }
                  ]
                }
              ]
            }
          ]
        },
        {
          "type": "heading",
          "attrs": {
            "level": 3
          },
          "content": [
            {
              "type": "text",
              "text": "3. Separate Business and Personal"
            }
          ]
        },
        {
          "type": "paragraph",
          "content": [
            {
              "type": "text",
              "text": "This is crucial. Open a dedicated business bank account and credit card. It makes tracking easier and provides liability protection."
            }
          ]
        },
        {
          "type": "callout",
          "attrs": {
            "variant": "warning"
          },
          "content": [
            {
              "type": "paragraph",
              "content": [
                {
                  "type": "text",
                  "text": "Mixing personal and business finances is one of the most common bookkeeping mistakes. Avoid it from day one."
                }
              ]
            }
          ]
        },
        {
          "type": "heading",
          "attrs": {
            "level": 3
          },
          "content": [
            {
              "type": "text",
              "text": "4. Reconcile Monthly"
            }
          ]
        },
        {
          "type": "paragraph",
          "content": [
            {
              "type": "text",
              "text": "Compare your records to your bank statements every month. This catches errors and ensures nothing slipped through the cracks."
            }
          ]
        },
        {
          "type": "heading",
          "attrs": {
            "level": 2
          },
          "content": [
            {
              "type": "text",
              "text": "Simple Tools That Work"
            }
          ]
        },
        {
          "type": "paragraph",
          "content": [
            {
              "type": "text",
              "text": "You don't need expensive software. Start with:"
            }
          ]
        },
        {
          "type": "bulletList",
          "content": [
            {
              "type": "listItem",
              "content": [
                {
                  "type": "paragraph",
                  "content": [
                    {
                      "type": "text",
                      "text": "A spreadsheet (Excel or Google Sheets)"
                    }
                  ]
                }
              ]
            },
            {
              "type": "listItem",
              "content": [
                {
                  "type": "paragraph",
                  "content": [
                    {
                      "type": "text",
                      "text": "A basic ledger book or printable template"
                    }
                  ]
                }
              ]
            },
            {
              "type": "listItem",
              "content": [
                {
                  "type": "paragraph",
                  "content": [
                    {
                      "type": "text",
                      "text": "A dedicated folder system for receipts"
                    }
                  ]
                }
              ]
            },
            {
              "type": "listItem",
              "content": [
                {
                  "type": "paragraph",
                  "content": [
                    {
                      "type": "text",
                      "text": "Your bank's transaction export feature"
                    }
                  ]
                }
              ]
            }
          ]
        },
        {
          "type": "heading",
          "attrs": {
            "level": 2
          },
          "content": [
            {
              "type": "text",
              "text": "When to Get Help"
            }
          ]
        },
        {
          "type": "paragraph",
          "content": [
            {
              "type": "text",
              "text": "Consider hiring a professional when:"
            }
          ]
        },
        {
          "type": "bulletList",
          "content": [
            {
              "type": "listItem",
              "content": [
                {
                  "type": "paragraph",
                  "content": [
                    {
                      "type": "text",
                      "text": "Your revenue exceeds $50,000/year"
                    }
                  ]
                }
              ]
            },
            {
              "type": "listItem",
              "content": [
                {
                  "type": "paragraph",
                  "content": [
                    {
                      "type": "text",
                      "text": "You have employees"
                    }
                  ]
                }
              ]
            },
            {
              "type": "listItem",
              "content": [
                {
                  "type": "paragraph",
                  "content": [
                    {
                      "type": "text",
                      "text": "You're dealing with complex tax situations"
                    }
                  ]
                }
              ]
            },
            {
              "type": "listItem",
              "content": [
                {
                  "type": "paragraph",
                  "content": [
                    {
                      "type": "text",
                      "text": "Bookkeeping takes more than 2-3 hours weekly"
                    }
                  ]
                }
              ]
            },
            {
              "type": "listItem",
              "content": [
                {
                  "type": "paragraph",
                  "content": [
                    {
                      "type": "text",
                      "text": "You're making financial decisions that need expert input"
                    }
                  ]
                }
              ]
            }
          ]
        },
        {
          "type": "callout",
          "attrs": {
            "variant": "info"
          },
          "content": [
            {
              "type": "paragraph",
              "content": [
                {
                  "type": "text",
                  "text": "Even if you hire help later, the habits you build now will make working with an accountant much more efficient."
                }
              ]
            }
          ]
        },
        {
          "type": "heading",
          "attrs": {
            "level": 2
          },
          "content": [
            {
              "type": "text",
              "text": "Get Started Today"
            }
          ]
        },
        {
          "type": "paragraph",
          "content": [
            {
              "type": "text",
              "text": "The best time to start organizing your finances is now. Pick one task from this guide and do it today. Small, consistent efforts add up to excellent financial habits."
            }
          ]
        }
      ]
    },
    "coverImageUrl": "/images/articles/bookkeeping-basics.jpg",
    "status": "published",
    "publishedAt": "2024-11-01T00:00:00.000Z",
    "seoTitle": "Bookkeeping Basics Without an Accountant",
    "seoDescription": "No accountant? No problem. Learn simple bookkeeping practices that keep your finances organized without professional help.",
    "tagIds": [],
    "legacySlug": "bookkeeping-basics-without-an-accountant"
  },
  {
    "title": "Keeping All Your Etsy Seller Finances in One Place",
    "slug": "etsy-seller-finances-in-one-place",
    "excerpt": "Stop juggling multiple spreadsheets. Learn how to centralize your Etsy business finances for clearer insights and easier tax prep.",
    "content": {
      "type": "doc",
      "content": [
        {
          "type": "paragraph",
          "content": [
            {
              "type": "text",
              "text": "If you're an Etsy seller, you know the financial complexity: Etsy fees, payment processing fees, shipping costs, supply expenses, and income from multiple sources. Keeping track of it all can feel overwhelming."
            }
          ]
        },
        {
          "type": "paragraph",
          "content": [
            {
              "type": "text",
              "text": "The solution? Centralization. Having one place where all your financial information lives makes everything easier—from daily operations to tax time."
            }
          ]
        },
        {
          "type": "heading",
          "attrs": {
            "level": 2
          },
          "content": [
            {
              "type": "text",
              "text": "The Problem with Scattered Finances"
            }
          ]
        },
        {
          "type": "paragraph",
          "content": [
            {
              "type": "text",
              "text": "Many Etsy sellers fall into these traps:"
            }
          ]
        },
        {
          "type": "bulletList",
          "content": [
            {
              "type": "listItem",
              "content": [
                {
                  "type": "paragraph",
                  "content": [
                    {
                      "type": "text",
                      "text": "Multiple spreadsheets that don't talk to each other"
                    }
                  ]
                }
              ]
            },
            {
              "type": "listItem",
              "content": [
                {
                  "type": "paragraph",
                  "content": [
                    {
                      "type": "text",
                      "text": "Receipts scattered across email, photos, and drawers"
                    }
                  ]
                }
              ]
            },
            {
              "type": "listItem",
              "content": [
                {
                  "type": "paragraph",
                  "content": [
                    {
                      "type": "text",
                      "text": "Etsy statements that don't match bank deposits"
                    }
                  ]
                }
              ]
            },
            {
              "type": "listItem",
              "content": [
                {
                  "type": "paragraph",
                  "content": [
                    {
                      "type": "text",
                      "text": "No clear picture of actual profit"
                    }
                  ]
                }
              ]
            },
            {
              "type": "listItem",
              "content": [
                {
                  "type": "paragraph",
                  "content": [
                    {
                      "type": "text",
                      "text": "Tax time panic"
                    }
                  ]
                }
              ]
            }
          ]
        },
        {
          "type": "heading",
          "attrs": {
            "level": 2
          },
          "content": [
            {
              "type": "text",
              "text": "Creating Your Financial Hub"
            }
          ]
        },
        {
          "type": "heading",
          "attrs": {
            "level": 3
          },
          "content": [
            {
              "type": "text",
              "text": "Step 1: Choose Your Primary Tool"
            }
          ]
        },
        {
          "type": "paragraph",
          "content": [
            {
              "type": "text",
              "text": "Pick ONE place for your financial records. Options include:"
            }
          ]
        },
        {
          "type": "bulletList",
          "content": [
            {
              "type": "listItem",
              "content": [
                {
                  "type": "paragraph",
                  "content": [
                    {
                      "type": "text",
                      "text": "A well-organized spreadsheet"
                    }
                  ]
                }
              ]
            },
            {
              "type": "listItem",
              "content": [
                {
                  "type": "paragraph",
                  "content": [
                    {
                      "type": "text",
                      "text": "Simple accounting software (Wave, QuickBooks Self-Employed)"
                    }
                  ]
                }
              ]
            },
            {
              "type": "listItem",
              "content": [
                {
                  "type": "paragraph",
                  "content": [
                    {
                      "type": "text",
                      "text": "A dedicated business ledger"
                    }
                  ]
                }
              ]
            }
          ]
        },
        {
          "type": "callout",
          "attrs": {
            "variant": "info"
          },
          "content": [
            {
              "type": "paragraph",
              "content": [
                {
                  "type": "text",
                  "text": "The best tool is the one you'll actually use consistently. Fancy software you ignore is worse than a simple spreadsheet you update weekly."
                }
              ]
            }
          ]
        },
        {
          "type": "heading",
          "attrs": {
            "level": 3
          },
          "content": [
            {
              "type": "text",
              "text": "Step 2: Set Up Your Categories"
            }
          ]
        },
        {
          "type": "paragraph",
          "content": [
            {
              "type": "text",
              "text": "Create categories that match your Etsy business:"
            }
          ]
        },
        {
          "type": "bulletList",
          "content": [
            {
              "type": "listItem",
              "content": [
                {
                  "type": "paragraph",
                  "content": [
                    {
                      "type": "text",
                      "text": "Income: Etsy sales, direct sales, other platforms"
                    }
                  ]
                }
              ]
            },
            {
              "type": "listItem",
              "content": [
                {
                  "type": "paragraph",
                  "content": [
                    {
                      "type": "text",
                      "text": "Fees: Etsy listing fees, transaction fees, payment processing"
                    }
                  ]
                }
              ]
            },
            {
              "type": "listItem",
              "content": [
                {
                  "type": "paragraph",
                  "content": [
                    {
                      "type": "text",
                      "text": "Supplies: Materials, packaging, labels"
                    }
                  ]
                }
              ]
            },
            {
              "type": "listItem",
              "content": [
                {
                  "type": "paragraph",
                  "content": [
                    {
                      "type": "text",
                      "text": "Shipping: Postage, packaging materials"
                    }
                  ]
                }
              ]
            },
            {
              "type": "listItem",
              "content": [
                {
                  "type": "paragraph",
                  "content": [
                    {
                      "type": "text",
                      "text": "Marketing: Ads, promoted listings"
                    }
                  ]
                }
              ]
            },
            {
              "type": "listItem",
              "content": [
                {
                  "type": "paragraph",
                  "content": [
                    {
                      "type": "text",
                      "text": "Tools: Software, equipment"
                    }
                  ]
                }
              ]
            }
          ]
        },
        {
          "type": "heading",
          "attrs": {
            "level": 3
          },
          "content": [
            {
              "type": "text",
              "text": "Step 3: Establish a Routine"
            }
          ]
        },
        {
          "type": "paragraph",
          "content": [
            {
              "type": "text",
              "text": "Consistency beats intensity. A quick 15-minute weekly routine works better than marathon monthly sessions:"
            }
          ]
        },
        {
          "type": "bulletList",
          "content": [
            {
              "type": "listItem",
              "content": [
                {
                  "type": "paragraph",
                  "content": [
                    {
                      "type": "text",
                      "text": "Download Etsy payment reports"
                    }
                  ]
                }
              ]
            },
            {
              "type": "listItem",
              "content": [
                {
                  "type": "paragraph",
                  "content": [
                    {
                      "type": "text",
                      "text": "Match deposits to sales"
                    }
                  ]
                }
              ]
            },
            {
              "type": "listItem",
              "content": [
                {
                  "type": "paragraph",
                  "content": [
                    {
                      "type": "text",
                      "text": "Log expenses"
                    }
                  ]
                }
              ]
            },
            {
              "type": "listItem",
              "content": [
                {
                  "type": "paragraph",
                  "content": [
                    {
                      "type": "text",
                      "text": "File/organize receipts"
                    }
                  ]
                }
              ]
            },
            {
              "type": "listItem",
              "content": [
                {
                  "type": "paragraph",
                  "content": [
                    {
                      "type": "text",
                      "text": "Note any questions or anomalies"
                    }
                  ]
                }
              ]
            }
          ]
        },
        {
          "type": "heading",
          "attrs": {
            "level": 2
          },
          "content": [
            {
              "type": "text",
              "text": "Understanding Etsy's Fee Structure"
            }
          ]
        },
        {
          "type": "paragraph",
          "content": [
            {
              "type": "text",
              "text": "Etsy takes several cuts from each sale:"
            }
          ]
        },
        {
          "type": "bulletList",
          "content": [
            {
              "type": "listItem",
              "content": [
                {
                  "type": "paragraph",
                  "content": [
                    {
                      "type": "text",
                      "text": "Listing fee: $0.20 per item"
                    }
                  ]
                }
              ]
            },
            {
              "type": "listItem",
              "content": [
                {
                  "type": "paragraph",
                  "content": [
                    {
                      "type": "text",
                      "text": "Transaction fee: 6.5% of sale price (including shipping)"
                    }
                  ]
                }
              ]
            },
            {
              "type": "listItem",
              "content": [
                {
                  "type": "paragraph",
                  "content": [
                    {
                      "type": "text",
                      "text": "Payment processing: 3% + $0.25 per transaction"
                    }
                  ]
                }
              ]
            },
            {
              "type": "listItem",
              "content": [
                {
                  "type": "paragraph",
                  "content": [
                    {
                      "type": "text",
                      "text": "Offsite ads fee: 12-15% (if applicable)"
                    }
                  ]
                }
              ]
            }
          ]
        },
        {
          "type": "callout",
          "attrs": {
            "variant": "warning"
          },
          "content": [
            {
              "type": "paragraph",
              "content": [
                {
                  "type": "text",
                  "text": "The fees add up! On a $20 sale with $5 shipping, you might pay $2.50+ in fees. Always factor this into your pricing."
                }
              ]
            }
          ]
        },
        {
          "type": "heading",
          "attrs": {
            "level": 2
          },
          "content": [
            {
              "type": "text",
              "text": "Reconciling Etsy with Your Bank"
            }
          ]
        },
        {
          "type": "paragraph",
          "content": [
            {
              "type": "text",
              "text": "Etsy deposits don't match individual sales. Here's how to reconcile:"
            }
          ]
        },
        {
          "type": "bulletList",
          "content": [
            {
              "type": "listItem",
              "content": [
                {
                  "type": "paragraph",
                  "content": [
                    {
                      "type": "text",
                      "text": "Download your Etsy payment account CSV"
                    }
                  ]
                }
              ]
            },
            {
              "type": "listItem",
              "content": [
                {
                  "type": "paragraph",
                  "content": [
                    {
                      "type": "text",
                      "text": "Match deposit dates to your bank statement"
                    }
                  ]
                }
              ]
            },
            {
              "type": "listItem",
              "content": [
                {
                  "type": "paragraph",
                  "content": [
                    {
                      "type": "text",
                      "text": "The deposit = sales - fees for that period"
                    }
                  ]
                }
              ]
            },
            {
              "type": "listItem",
              "content": [
                {
                  "type": "paragraph",
                  "content": [
                    {
                      "type": "text",
                      "text": "Record the gross sales AND fees separately for accurate profit tracking"
                    }
                  ]
                }
              ]
            }
          ]
        },
        {
          "type": "heading",
          "attrs": {
            "level": 2
          },
          "content": [
            {
              "type": "text",
              "text": "Tax Time Preparation"
            }
          ]
        },
        {
          "type": "paragraph",
          "content": [
            {
              "type": "text",
              "text": "Good centralized records make taxes simple:"
            }
          ]
        },
        {
          "type": "bulletList",
          "content": [
            {
              "type": "listItem",
              "content": [
                {
                  "type": "paragraph",
                  "content": [
                    {
                      "type": "text",
                      "text": "Total income is clearly documented"
                    }
                  ]
                }
              ]
            },
            {
              "type": "listItem",
              "content": [
                {
                  "type": "paragraph",
                  "content": [
                    {
                      "type": "text",
                      "text": "Deductible expenses are categorized"
                    }
                  ]
                }
              ]
            },
            {
              "type": "listItem",
              "content": [
                {
                  "type": "paragraph",
                  "content": [
                    {
                      "type": "text",
                      "text": "Receipts are organized and accessible"
                    }
                  ]
                }
              ]
            },
            {
              "type": "listItem",
              "content": [
                {
                  "type": "paragraph",
                  "content": [
                    {
                      "type": "text",
                      "text": "Etsy provides 1099-K for verification"
                    }
                  ]
                }
              ]
            }
          ]
        },
        {
          "type": "heading",
          "attrs": {
            "level": 2
          },
          "content": [
            {
              "type": "text",
              "text": "Start Today"
            }
          ]
        },
        {
          "type": "paragraph",
          "content": [
            {
              "type": "text",
              "text": "Don't wait for the perfect system. Start with these three actions:"
            }
          ]
        },
        {
          "type": "bulletList",
          "content": [
            {
              "type": "listItem",
              "content": [
                {
                  "type": "paragraph",
                  "content": [
                    {
                      "type": "text",
                      "text": "Download your last month's Etsy payment report"
                    }
                  ]
                }
              ]
            },
            {
              "type": "listItem",
              "content": [
                {
                  "type": "paragraph",
                  "content": [
                    {
                      "type": "text",
                      "text": "Create a simple spreadsheet with income and expense columns"
                    }
                  ]
                }
              ]
            },
            {
              "type": "listItem",
              "content": [
                {
                  "type": "paragraph",
                  "content": [
                    {
                      "type": "text",
                      "text": "Commit to 15 minutes weekly for updates"
                    }
                  ]
                }
              ]
            }
          ]
        },
        {
          "type": "paragraph",
          "content": [
            {
              "type": "text",
              "text": "A centralized, simple system you maintain consistently will always beat a complex system you ignore."
            }
          ]
        }
      ]
    },
    "coverImageUrl": "/images/articles/etsy-finances.jpg",
    "status": "published",
    "publishedAt": "2024-10-15T00:00:00.000Z",
    "seoTitle": "Keeping All Your Etsy Seller Finances in One Place",
    "seoDescription": "Stop juggling multiple spreadsheets. Learn how to centralize your Etsy business finances for clearer insights and easier tax prep.",
    "tagIds": [],
    "legacySlug": "etsy-seller-finances-in-one-place"
  }
]